image_croquis/__init__.py
image_croquis/image_croquis.py
image_croquis-0.0.6.dist-info/LICENSE
image_croquis-0.0.6.dist-info/METADATA
image_croquis-0.0.6.dist-info/WHEEL
image_croquis-0.0.6.dist-info/entry_points.txt
image_croquis-0.0.6.dist-info/top_level.txt
image_croquis-0.0.6.dist-info/RECORD
